pg_simple_auth/__init__.py
pg_simple_auth/auth.py
pg_simple_auth-0.1.4.dist-info/licenses/LICENSE
pg_simple_auth-0.1.4.dist-info/METADATA
pg_simple_auth-0.1.4.dist-info/WHEEL
pg_simple_auth-0.1.4.dist-info/top_level.txt
pg_simple_auth-0.1.4.dist-info/RECORD
