Metadata-Version: 2.4
Name: pg_simple_auth
Version: 0.1.4
Summary: A simple asynchronous authentication module for PostgreSQL
Home-page: https://github.com/255BITS/pg_simple_auth
Author: Martyn Garcia
Author-email: martyn@255bits.com
License: MIT
Classifier: Programming Language :: Python :: 3
Classifier: License :: OSI Approved :: MIT License
Classifier: Operating System :: OS Independent
Classifier: Framework :: AsyncIO
Classifier: Intended Audience :: Developers
Classifier: Topic :: Software Development :: Libraries :: Python Modules
Classifier: Topic :: Internet :: WWW/HTTP :: Session
Classifier: Topic :: Security :: Cryptography
Requires-Python: >=3.8
License-File: LICENSE
Requires-Dist: asyncpg>=0.21
Requires-Dist: passlib>=1.7.4
Requires-Dist: PyJWT>=2.1.0
Dynamic: author
Dynamic: author-email
Dynamic: classifier
Dynamic: description
Dynamic: description-content-type
Dynamic: home-page
Dynamic: license
Dynamic: license-file
Dynamic: requires-dist
Dynamic: requires-python
Dynamic: summary
